LICENSE.txt
MANIFEST.in
setup.py
pynxc/__init__.py
pynxc/ast_template.py
pynxc/definitions.py
pynxc/first_pass.py
pynxc/pynxc.py
pynxc/second_pass.py
pynxc.egg-info/PKG-INFO
pynxc.egg-info/SOURCES.txt
pynxc.egg-info/dependency_links.txt
pynxc.egg-info/entry_points.txt
pynxc.egg-info/top_level.txt
pynxc/nxc/README
pynxc/nxc/darwin/nbc
pynxc/nxc/darwin/nxtcom
pynxc/nxc/linux2/nbc
pynxc/nxc/win32/nbc.exe