Metadata-Version: 1.0
Name: pynxc
Version: 0.1.7
Summary: A Python to NXC Converter for programmingLEGO MINDSTORMS Robots
Home-page: https://github.com/xlcteam/pynxc
Author: Marek Šuppa
Author-email: marek@suppa.sk
License: UNKNOWN
Platform: UNKNOWN
